PyOFC2glb-0.1.6.dev0.dist-info/METADATA
PyOFC2glb-0.1.6.dev0.dist-info/RECORD
PyOFC2glb-0.1.6.dev0.dist-info/WHEEL
PyOFC2glb-0.1.6.dev0.dist-info/entry_points.txt
PyOFC2glb-0.1.6.dev0.dist-info/top_level.txt
pyofc2/__init__.py
pyofc2/ofc2.py
