Metadata-Version: 2.1
Name: PyOFC2glb
Version: 0.1.6.dev0
Summary: Python library for Open Flash Chart 2
Home-page: http://pradeepgowda.com/
Author: Pradeep Kishore Gowda
Author-email: pradeep+pyofc2@btbytes.com
License: MIT
Keywords: flash graphics charts json visualisation visualization internet
Platform: UNKNOWN
Classifier: Development Status :: 4 - Beta
Classifier: License :: OSI Approved :: MIT License
Classifier: Operating System :: OS Independent
Classifier: Topic :: Internet
Requires-Dist: anyjson (>=0.1)
